b_utils_infra/__init__.py
b_utils_infra/ai.py
b_utils_infra/generic.py
b_utils_infra/logging.py
b_utils_infra/pandas.py
b_utils_infra/services.py
b_utils_infra/translation.py
b_utils_infra-0.2.1.dist-info/LICENSE
b_utils_infra-0.2.1.dist-info/METADATA
b_utils_infra-0.2.1.dist-info/WHEEL
b_utils_infra-0.2.1.dist-info/top_level.txt
b_utils_infra-0.2.1.dist-info/RECORD
