Metadata-Version: 2.1
Name: b-utils-infra
Version: 0.2.1
Summary: A collection of utility functions and classes for Python projects.
Home-page: https://github.com/Fahadukr/b-utils-infra
Author: Fahad Mawlood
Author-email: fahadukr@gmail.com
Classifier: Programming Language :: Python :: 3
Classifier: License :: OSI Approved :: MIT License
Classifier: Operating System :: OS Independent
Requires-Python: >=3.10
License-File: LICENSE
Requires-Dist: SQLAlchemy >=2.0.0
Requires-Dist: pandas >=2.0.0
Requires-Dist: numpy <2.0.0
Requires-Dist: google-cloud-translate >=3.12.0
Requires-Dist: openai >=1.11.1
Requires-Dist: slack-sdk
Requires-Dist: tiktoken
Requires-Dist: deepl
Requires-Dist: google-api-python-client
Requires-Dist: google-auth-httplib2
Requires-Dist: google-auth-oauthlib
